odoo/addons/sales_team_operating_unit/README.rst
odoo/addons/sales_team_operating_unit/__init__.py
odoo/addons/sales_team_operating_unit/__manifest__.py
odoo/addons/sales_team_operating_unit/demo/sales_team_demo.xml
odoo/addons/sales_team_operating_unit/i18n/pt.po
odoo/addons/sales_team_operating_unit/i18n/sales_team_operating_unit.pot
odoo/addons/sales_team_operating_unit/models/__init__.py
odoo/addons/sales_team_operating_unit/models/crm_team.py
odoo/addons/sales_team_operating_unit/readme/CONTRIBUTORS.rst
odoo/addons/sales_team_operating_unit/readme/DESCRIPTION.rst
odoo/addons/sales_team_operating_unit/readme/USAGE.rst
odoo/addons/sales_team_operating_unit/security/crm_security.xml
odoo/addons/sales_team_operating_unit/static/description/icon.png
odoo/addons/sales_team_operating_unit/static/description/index.html
odoo/addons/sales_team_operating_unit/tests/__init__.py
odoo/addons/sales_team_operating_unit/tests/test_crm_team_operating_unit.py
odoo/addons/sales_team_operating_unit/views/crm_team_view.xml
odoo12_addon_sales_team_operating_unit-12.0.1.1.2.dist-info/METADATA
odoo12_addon_sales_team_operating_unit-12.0.1.1.2.dist-info/WHEEL
odoo12_addon_sales_team_operating_unit-12.0.1.1.2.dist-info/top_level.txt
odoo12_addon_sales_team_operating_unit-12.0.1.1.2.dist-info/RECORD
