Metadata-Version: 2.1
Name: odoo12-addon-sales-team-operating-unit
Version: 12.0.1.1.2
Summary: Sales Team Operating Unit
Home-page: https://github.com/OCA/operating-unit
Author: Eficent, SerpentCS,Odoo Community Association (OCA)
Author-email: support@odoo-community.org
License: LGPL-3
Platform: UNKNOWN
Classifier: Programming Language :: Python
Classifier: Framework :: Odoo
Classifier: License :: OSI Approved :: GNU Lesser General Public License v3 (LGPLv3)
Requires-Python: >=3.5
Requires-Dist: odoo12-addon-operating-unit
Requires-Dist: odoo (<12.1dev,>=12.0a)
